{
  "schema_version": 2,
  "task_id": "tranche-fronted-src-pages-permissiongroupmanagem-20260408T082611",
  "mode": "full",
  "status": "completed",
  "current_phase": null,
  "phase_statuses": [
    {
      "phase_id": "P1",
      "title": "Split the permission group page into focused render components",
      "status": "completed",
      "objective": "Move major page render sections into bounded feature components while keeping `PermissionGroupManagement.js` as the composition page and preserving `usePermissionGroupManagementPage` as the page-state owner.",
      "owned_paths": [],
      "dependencies": [],
      "deliverables": [],
      "evidence_expectation": "",
      "acceptance_criteria": [
        {
          "ac_id": "P1-AC1",
          "text": "`PermissionGroupManagement.js` no longer directly owns the toolbar, sidebar wrapper, status/delete-confirmation block, and editor panel markup in one file.",
          "status": "completed",
          "evidence": [
            "execution-log.md#Phase-P1",
            "test-report.md#T1"
          ]
        },
        {
          "ac_id": "P1-AC2",
          "text": "the page continues to consume the same `usePermissionGroupManagementPage` state/action contract without page-level behavior changes.",
          "status": "completed",
          "evidence": [
            "execution-log.md#Phase-P1",
            "test-report.md#T1"
          ]
        },
        {
          "ac_id": "P1-AC3",
          "text": "toolbar actions, pending-delete confirmation, and editor rendering continue surfacing the existing states instead of introducing fallback paths.",
          "status": "completed",
          "evidence": [
            "execution-log.md#Phase-P1",
            "test-report.md#T1"
          ]
        }
      ],
      "evidence": [
        "execution-log.md#Phase-P1"
      ],
      "notes": "- - Split the permission-group route page into focused sidebar and editor components while preserving the page-hook contract.",
      "last_reviewed_at": "2026-04-08T08:30:45"
    },
    {
      "phase_id": "P2",
      "title": "Focused frontend regression validation and task evidence",
      "status": "completed",
      "objective": "Prove the bounded page refactor preserved current permission-group page behavior.",
      "owned_paths": [],
      "dependencies": [],
      "deliverables": [],
      "evidence_expectation": "",
      "acceptance_criteria": [
        {
          "ac_id": "P2-AC1",
          "text": "focused permission-group page Jest suites pass against the final code state.",
          "status": "completed",
          "evidence": [
            "execution-log.md#Phase-P2",
            "test-report.md#T1"
          ]
        },
        {
          "ac_id": "P2-AC2",
          "text": "task artifacts record the exact commands run, verified acceptance coverage, and bounded residual risk.",
          "status": "completed",
          "evidence": [
            "execution-log.md#Phase-P2",
            "test-report.md#T1"
          ]
        }
      ],
      "evidence": [
        "execution-log.md#Phase-P2"
      ],
      "notes": "- - Focused Jest evidence recorded for the permission-group page-hook and page suites with bounded residual risk documented in task artifacts.",
      "last_reviewed_at": "2026-04-08T08:30:56"
    }
  ],
  "planner_review_status": "approved",
  "test_status": "passed",
  "blocking_prereqs": [],
  "iteration_counts": {
    "planner_revisions": 0,
    "executor_loops": 2,
    "test_loops": 1
  },
  "created_at": "2026-04-08T08:26:11",
  "updated_at": "2026-04-08T08:31:20",
  "branch": "int_latest",
  "baseline_revision": "3619b8169b862232147c8e7a8d7bca3608a3d8f3",
  "workspace_root": "D:\\ProjectPackage\\RagflowAuth",
  "tasks_root": "D:\\ProjectPackage\\RagflowAuth\\docs\\tasks",
  "task_dir": "D:\\ProjectPackage\\RagflowAuth\\docs\\tasks\\tranche-fronted-src-pages-permissiongroupmanagem-20260408T082611",
  "goal": "继续进行前后端重构直到重构结束：本 tranche 聚焦 fronted/src/pages/PermissionGroupManagement.js，拆分工具栏、文件夹树侧栏、状态与删除确认区域、编辑器面板等页面区块，保持 usePermissionGroupManagementPage 契约与现有 Jest 测试行为稳定",
  "artifacts": {
    "prd": "D:\\ProjectPackage\\RagflowAuth\\docs\\tasks\\tranche-fronted-src-pages-permissiongroupmanagem-20260408T082611\\prd.md",
    "test_plan": "D:\\ProjectPackage\\RagflowAuth\\docs\\tasks\\tranche-fronted-src-pages-permissiongroupmanagem-20260408T082611\\test-plan.md",
    "task_state": "D:\\ProjectPackage\\RagflowAuth\\docs\\tasks\\tranche-fronted-src-pages-permissiongroupmanagem-20260408T082611\\task-state.json",
    "execution_log": "D:\\ProjectPackage\\RagflowAuth\\docs\\tasks\\tranche-fronted-src-pages-permissiongroupmanagem-20260408T082611\\execution-log.md",
    "test_report": "D:\\ProjectPackage\\RagflowAuth\\docs\\tasks\\tranche-fronted-src-pages-permissiongroupmanagem-20260408T082611\\test-report.md"
  }
}
